logger_bro/__init__.py
logger_bro/logger.py
logger_bro-0.0.7.dist-info/METADATA
logger_bro-0.0.7.dist-info/WHEEL
logger_bro-0.0.7.dist-info/top_level.txt
logger_bro-0.0.7.dist-info/RECORD
