Metadata-Version: 2.1
Name: logger-bro
Version: 0.0.7
Summary: A logging package using Loki for Python
Author: Charis Giaralis
Author-email: charis.giaralis@gmail.com
License: UNKNOWN
Keywords: python,logger
Platform: UNKNOWN
Classifier: Development Status :: 3 - Alpha
Classifier: Intended Audience :: Education
Classifier: Programming Language :: Python :: 2
Classifier: Programming Language :: Python :: 3
Classifier: Operating System :: MacOS :: MacOS X
Classifier: Operating System :: Microsoft :: Windows
Requires-Dist: python-logging-loki
